{
    "academic": [
        {
            "title": "[科学网] 中国科学院党组召开理论学习中心组集体学习会学习脑机接口领域前沿发展态势",
            "url": "https://www.cas.cn/yw/202606/t20260609_5112183.shtml"
        },
        {
            "title": "[科学网] 徐天衡：在6G浪潮中找到自己的“信号”",
            "url": "https://news.sciencenet.cn/htmlnews/2026/6/566258.shtm"
        },
        {
            "title": "[科学网] 封面丨精氨酸界面调控策略提升SiOx负极循环稳定性",
            "url": "https://news.sciencenet.cn/htmlnews/2026/6/565896.shtm"
        },
        {
            "title": "[科学网] 无线芯片嵌入单晶金刚石后突破散热瓶颈",
            "url": "https://news.sciencenet.cn/htmlnews/2026/6/566257.shtm"
        },
        {
            "title": "[科学网] 北京高校大学生就业创业研究课题拟立项名单公示",
            "url": "https://news.sciencenet.cn/htmlnews/2026/6/566256.shtm"
        },
        {
            "title": "[科学网] 2026年吉林省教学成果奖拟表彰成果名单公示",
            "url": "https://news.sciencenet.cn/htmlnews/2026/6/566255.shtm"
        },
        {
            "title": "[科学网] 多个硕博拿学位不再“唯论文”",
            "url": "https://news.sciencenet.cn/htmlnews/2026/6/566254.shtm"
        },
        {
            "title": "[科学网] 2025年度宁夏科学技术奖初评结果公示",
            "url": "https://news.sciencenet.cn/htmlnews/2026/6/566253.shtm"
        },
        {
            "title": "[中科院] 知识产权与科技成果转化网",
            "url": "http://www.casip.ac.cn/"
        },
        {
            "title": "[中科院] 审计与监督局（党组巡视工作领导小组办公室）",
            "url": "https://jianshen.cas.cn/"
        },
        {
            "title": "[中科院] 中央纪委国家监委驻中国科学院纪检监察组",
            "url": "https://jijianzu.cas.cn/"
        },
        {
            "title": "[中科院] 中国科学院杰出科技成就奖",
            "url": "https://www.cas.cn//kxyj/kj/casjc/"
        },
        {
            "title": "[中科院] 中国科学院国际科技合作奖",
            "url": "https://www.cas.cn//kxyj/kj/cashz/"
        },
        {
            "title": "[中科院] 低约束可穿戴传感器贴片研究获进展",
            "url": "https://www.cas.cn/../../syky/202606/t20260608_5111972.shtml"
        },
        {
            "title": "[中科院] 研究发现肠道菌群调控高海拔灵长类适应性产热机制",
            "url": "https://www.cas.cn/../../syky/202606/t20260602_5111472.shtml"
        },
        {
            "title": "[中科院] 研究实现科研图表数据自动化高精度重构",
            "url": "https://www.cas.cn/../../syky/202606/t20260608_5111976.shtml"
        }
    ],
    "policy": [
        {
            "title": "[科技政策] 京ICP备05070218号",
            "url": "https://beian.miit.gov.cn/#/Integrated/index"
        },
        {
            "title": "[科技政策] 京公网安备11010202000001号",
            "url": "http://www.beian.gov.cn/portal/registerSystemInfo?recordcode=11010202000001"
        }
    ],
    "update_time": "2026-06-10 01:59:17"
}