{
    "academic": [
        {
            "title": "[科学网] 中国科学家领衔破解地球科学领域“悬案”",
            "url": "https://news.sciencenet.cn/htmlnews/2026/4/563772.shtm"
        },
        {
            "title": "[科学网] 余玉刚团队：要想“顶天”，先要“立地”",
            "url": "https://news.sciencenet.cn/htmlnews/2026/4/563771.shtm"
        },
        {
            "title": "[科学网] 直播预告丨Cell Press Live：关键矿物与循环战略",
            "url": "https://news.sciencenet.cn/htmlnews/2026/4/563773.shtm"
        },
        {
            "title": "[科学网] 科研绘图教程｜这样画核小体更高效！",
            "url": "https://news.sciencenet.cn/htmlnews/2026/4/563488.shtm"
        },
        {
            "title": "[科学网] 中国青年五四奖章等评选结果揭晓，多位科研人员入...",
            "url": "https://news.sciencenet.cn/htmlnews/2026/4/563795.shtm"
        },
        {
            "title": "[科学网] 信息科大党委副书记于世洁拟任青海省属高校班子正...",
            "url": "https://news.sciencenet.cn/htmlnews/2026/4/563794.shtm"
        },
        {
            "title": "[科学网] 233人被授予2025年度“茅以升科学技术奖”",
            "url": "https://news.sciencenet.cn/htmlnews/2026/4/563793.shtm"
        },
        {
            "title": "[科学网] 肠道微生物组变化可预示帕金森病早期发展",
            "url": "https://news.sciencenet.cn/htmlnews/2026/4/563777.shtm"
        },
        {
            "title": "[中科院] 知识产权与科技成果转化网",
            "url": "http://www.casip.ac.cn/"
        },
        {
            "title": "[中科院] 审计与监督局（党组巡视工作领导小组办公室）",
            "url": "https://jianshen.cas.cn/"
        },
        {
            "title": "[中科院] 中央纪委国家监委驻中国科学院纪检监察组",
            "url": "https://jijianzu.cas.cn/"
        },
        {
            "title": "[中科院] 中国科学院杰出科技成就奖",
            "url": "https://www.cas.cn//kxyj/kj/casjc/"
        },
        {
            "title": "[中科院] 中国科学院国际科技合作奖",
            "url": "https://www.cas.cn//kxyj/kj/cashz/"
        },
        {
            "title": "[中科院] 科学家绘制大脑星形胶质细胞转录因子功能图谱",
            "url": "https://www.cas.cn/../../syky/202604/t20260424_5108049.shtml"
        },
        {
            "title": "[中科院] 研究揭示内源信使调控膜损伤与细胞死亡新机制",
            "url": "https://www.cas.cn/../../syky/202604/t20260422_5107567.shtml"
        },
        {
            "title": "[中科院] 靶向特定蛋白互作界面抑制乙肝病毒的研究获进展",
            "url": "https://www.cas.cn/../../syky/202604/t20260423_5107649.shtml"
        }
    ],
    "policy": [
        {
            "title": "[科技政策] 京ICP备05070218号",
            "url": "https://beian.miit.gov.cn/#/Integrated/index"
        },
        {
            "title": "[科技政策] 京公网安备11010202000001号",
            "url": "http://www.beian.gov.cn/portal/registerSystemInfo?recordcode=11010202000001"
        }
    ],
    "update_time": "2026-04-27 07:59:55"
}