{
    "academic": [
        {
            "title": "[科学网] 中国科学院第二十二次院士大会闭幕",
            "url": "https://www.cas.cn/yw/202607/t20260712_5115376.shtml"
        },
        {
            "title": "[科学网] 追本溯源、观照万物、立足前沿",
            "url": "https://news.sciencenet.cn/htmlnews/2026/7/568086.shtm"
        },
        {
            "title": "[科学网] 《水生生物学报》：南极磷虾还能存够“过冬粮”吗...",
            "url": "https://news.sciencenet.cn/htmlnews/2026/7/567819.shtm"
        },
        {
            "title": "[科学网] 丘成桐：人才培养改革不是上名校的捷径",
            "url": "https://news.sciencenet.cn/htmlnews/2026/7/568088.shtm"
        },
        {
            "title": "[科学网] 通用生物医学AI智能体可自主执行科研任务",
            "url": "https://news.sciencenet.cn/htmlnews/2026/7/568087.shtm"
        },
        {
            "title": "[科学网] 拟录用博士被质疑后，安徽大学公示网页已无权限访...",
            "url": "https://news.sciencenet.cn/htmlnews/2026/7/568084.shtm"
        },
        {
            "title": "[科学网] 新理论破解无血管期黄体能量来源之谜",
            "url": "https://news.sciencenet.cn/htmlnews/2026/7/568083.shtm"
        },
        {
            "title": "[科学网] 一周热闻回顾（2026年7月12日）",
            "url": "https://news.sciencenet.cn/htmlnews/2026/7/568082.shtm"
        },
        {
            "title": "[中科院] 知识产权与科技成果转化网",
            "url": "http://www.casip.ac.cn/"
        },
        {
            "title": "[中科院] 审计与监督局（党组巡视工作领导小组办公室）",
            "url": "https://jianshen.cas.cn/"
        },
        {
            "title": "[中科院] 中央纪委国家监委驻中国科学院纪检监察组",
            "url": "https://jijianzu.cas.cn/"
        },
        {
            "title": "[中科院] 中国科学院杰出科技成就奖",
            "url": "https://www.cas.cn//kxyj/kj/casjc/"
        },
        {
            "title": "[中科院] 中国科学院国际科技合作奖",
            "url": "https://www.cas.cn//kxyj/kj/cashz/"
        },
        {
            "title": "[中科院] 研究发现近日太阳风小型密度扰动的传播特征差异",
            "url": "https://www.cas.cn/../../syky/202607/t20260709_5115108.shtml"
        },
        {
            "title": "[中科院] 研究解析人端粒杂合四链体高分辨三维结构",
            "url": "https://www.cas.cn/../../syky/202607/t20260706_5114646.shtml"
        },
        {
            "title": "[中科院] 研究阐明镍与钴加速黄铁矿形成的作用机制",
            "url": "https://www.cas.cn/../../syky/202606/t20260617_5112738.shtml"
        }
    ],
    "policy": [
        {
            "title": "[科技政策] 京ICP备05070218号",
            "url": "https://beian.miit.gov.cn/#/Integrated/index"
        },
        {
            "title": "[科技政策] 京公网安备11010202000001号",
            "url": "http://www.beian.gov.cn/portal/registerSystemInfo?recordcode=11010202000001"
        }
    ],
    "update_time": "2026-07-13 01:19:54"
}