{
    "academic": [
        {
            "title": "[科学网] 填平思维鸿沟，他们为科学家创业“架桥”",
            "url": "https://news.sciencenet.cn/htmlnews/2026/4/563334.shtm"
        },
        {
            "title": "[科学网] 2026突破奖揭晓！3位华人女性数学家获奖",
            "url": "https://news.sciencenet.cn/htmlnews/2026/4/563326.shtm"
        },
        {
            "title": "[科学网] 从零开始学！手把手教你画水凝胶结构",
            "url": "https://news.sciencenet.cn/htmlnews/2026/4/563124.shtm"
        },
        {
            "title": "[科学网] 天津市征集2026年自然科学基金项目",
            "url": "https://news.sciencenet.cn/htmlnews/2026/4/563350.shtm"
        },
        {
            "title": "[科学网] 浙江省自然科学基金委员会委员调整，施一公等在列",
            "url": "https://news.sciencenet.cn/htmlnews/2026/4/563347.shtm"
        },
        {
            "title": "[科学网] 11个省市区公示第四届全国创新争先奖推荐对象",
            "url": "https://news.sciencenet.cn/htmlnews/2026/4/563346.shtm"
        },
        {
            "title": "[科学网] 16个项目提前验收，湖南省自科基金项目变更公示",
            "url": "https://news.sciencenet.cn/htmlnews/2026/4/563345.shtm"
        },
        {
            "title": "[科学网] 3930万元，海南支持柔性引才创新平台项目22项",
            "url": "https://news.sciencenet.cn/htmlnews/2026/4/563344.shtm"
        },
        {
            "title": "[中科院] 知识产权与科技成果转化网",
            "url": "http://www.casip.ac.cn/"
        },
        {
            "title": "[中科院] 审计与监督局（党组巡视工作领导小组办公室）",
            "url": "https://jianshen.cas.cn/"
        },
        {
            "title": "[中科院] 中央纪委国家监委驻中国科学院纪检监察组",
            "url": "https://jijianzu.cas.cn/"
        },
        {
            "title": "[中科院] 中国科学院杰出科技成就奖",
            "url": "https://www.cas.cn//kxyj/kj/casjc/"
        },
        {
            "title": "[中科院] 中国科学院国际科技合作奖",
            "url": "https://www.cas.cn//kxyj/kj/cashz/"
        },
        {
            "title": "[中科院] 研究发现大脑皮层双梯度组织规律",
            "url": "https://www.cas.cn/../../syky/202604/t20260417_5107236.shtml"
        },
        {
            "title": "[中科院] 研究开发出关键金属绿色提取新方法",
            "url": "https://www.cas.cn/../../syky/202604/t20260417_5107235.shtml"
        },
        {
            "title": "[中科院] 科学家制备出用于热管理可打印的碳纳米管超级塑料",
            "url": "https://www.cas.cn/../../syky/202604/t20260417_5107232.shtml"
        }
    ],
    "policy": [
        {
            "title": "[科技政策] 京ICP备05070218号",
            "url": "https://beian.miit.gov.cn/#/Integrated/index"
        },
        {
            "title": "[科技政策] 京公网安备11010202000001号",
            "url": "http://www.beian.gov.cn/portal/registerSystemInfo?recordcode=11010202000001"
        }
    ],
    "update_time": "2026-04-20 07:45:54"
}